plateauutils/__init__.py
plateauutils/cli.py
plateauutils/abc/__init__.py
plateauutils/abc/numpy_tile_parser.py
plateauutils/abc/plateau_parser.py
plateauutils/abc/polygon_to_list.py
plateauutils/citygmlfinder/__init__.py
plateauutils/citygmlfinder/from_reearth_cms.py
plateauutils/citygmlfinder/tests/data1.json
plateauutils/citygmlfinder/tests/data2.json
plateauutils/citygmlfinder/tests/data3.json
plateauutils/citygmlfinder/tests/data4.json
plateauutils/citygmlfinder/tests/test_from_reearth_cms.py
plateauutils/flood_converter/__init__.py
plateauutils/flood_converter/flood_to_3dtiles.py
plateauutils/flood_converter/flood_to_png.py
plateauutils/flood_converter/flood_to_xyz.py
plateauutils/flood_converter/tests/__init__.py
plateauutils/flood_converter/tests/test_flood_to_3dtiles.py
plateauutils/flood_converter/tests/test_flood_to_xyz.py
plateauutils/flood_converter/tests/fixtures/15/28264/13160.npz
plateauutils/mesh_geocorder/__init__.py
plateauutils/mesh_geocorder/geo_to_mesh.py
plateauutils/mesh_geocorder/polygon_to_meshcode_list.py
plateauutils/mesh_geocorder/tests/__init__.py
plateauutils/mesh_geocorder/tests/test_geo_to_mesh.py
plateauutils/mesh_geocorder/tests/test_polygon_to_meshcode_list.py
plateauutils/parser/__init__.py
plateauutils/parser/city_gml_parser.py
plateauutils/parser/mvt_tile_parser.py
plateauutils/parser/tests/__init__.py
plateauutils/parser/tests/test_city_gml_parser.py
plateauutils/parser/tests/test_mvt_tile_parser.py
plateauutils/tests/__init__.py
plateauutils/tests/test_cli.py
plateauutils/tile_list/__init__.py
plateauutils/tile_list/geo_to_tile.py
plateauutils/tile_list/polygon_to_tile_list.py
plateauutils/tile_list/tests/__init__.py
plateauutils/tile_list/tests/test_geo_to_tile.py
plateauutils/tile_list/tests/test_polygon_to_tile_list.py
plateauutils-0.0.15.dist-info/METADATA
plateauutils-0.0.15.dist-info/WHEEL
plateauutils-0.0.15.dist-info/licenses/LICENSE
plateauutils-0.0.15.dist-info/RECORD
