Metadata-Version: 2.1
Name: plateauutils
Version: 0.0.15
Summary: A collection of utilities for the Plateau project
Project-URL: Homepage, https://eukarya-inc.github.io/plateauutils/
Project-URL: Bug Reports, https://github.com/eukarya-inc/plateauutils/issues
Project-URL: Source, https://github.com/eukarya-inc/plateauutils
Author: Eukarya Inc.
License:                                  Apache License
License-File: LICENSE
Keywords: plateau
Classifier: Development Status :: 2 - Pre-Alpha
Classifier: Programming Language :: Python :: 3
Requires-Python: >=3.9
Requires-Dist: click
Requires-Dist: numpy
Requires-Dist: pandas
Requires-Dist: pillow
Requires-Dist: py3dtiles
Requires-Dist: pyproj
Requires-Dist: reearthcmsapi
Requires-Dist: requests
Requires-Dist: shapely
Requires-Dist: tqdm
